{"QuestionId":"q1377","Parse":{"TopicEntityName":"Remo ","TopicEntityMid":"<http://dbpedia.org/resource/Remo>","InferentialChain":["famous","musicians","play","remo"],"Constraints":[],"Answers":[{"AnswerType":"Entity","AnswerArgument":"<http://dbpedia.org/resource/Neil_Peart>","EntityName":"Neil Peart"},{"AnswerType":"Entity","AnswerArgument":"<http://dbpedia.org/resource/Ringo_Starr>","EntityName":"Ringo Starr"},{"AnswerType":"Entity","AnswerArgument":"<http://dbpedia.org/resource/Tommy_Lee>","EntityName":"Tommy Lee"},{"AnswerType":"Entity","AnswerArgument":"<http://dbpedia.org/resource/Don_Henley>","EntityName":"Don Henley"},{"AnswerType":"Entity","AnswerArgument":"<http://dbpedia.org/resource/Karen_Carpenter>","EntityName":"Karen Carpenter"},{"AnswerType":"Entity","AnswerArgument":"<http://dbpedia.org/resource/Caroline_Corr>","EntityName":"Caroline Corr"},{"AnswerType":"Entity","AnswerArgument":"<http://dbpedia.org/resource/Patty_Schemel>","EntityName":"Patty Schemel"},{"AnswerType":"Entity","AnswerArgument":"<http://dbpedia.org/resource/Darrin_Pfeiffer>","EntityName":"Darrin Pfeiffer"},{"AnswerType":"Entity","AnswerArgument":"<http://dbpedia.org/resource/Roger_Taylor_(Queen_drummer)>","EntityName":"Roger Taylor "},{"AnswerType":"Entity","AnswerArgument":"<http://dbpedia.org/resource/Joey_Castillo>","EntityName":"Joey Castillo"},{"AnswerType":"Entity","AnswerArgument":"<http://dbpedia.org/resource/Ray_Luzier>","EntityName":"Ray Luzier"},{"AnswerType":"Entity","AnswerArgument":"<http://dbpedia.org/resource/Brent_Fitz>","EntityName":"Brent Fitz"},{"AnswerType":"Entity","AnswerArgument":"<http://dbpedia.org/resource/Derek_Roddy>","EntityName":"Derek Roddy"},{"AnswerType":"Entity","AnswerArgument":"<http://dbpedia.org/resource/Carter_Beauford>","EntityName":"Carter Beauford"},{"AnswerType":"Entity","AnswerArgument":"<http://dbpedia.org/resource/Bev_Bevan>","EntityName":"Bev Bevan"},{"AnswerType":"Entity","AnswerArgument":"<http://dbpedia.org/resource/Ilan_Rubin>","EntityName":"Ilan Rubin"},{"AnswerType":"Entity","AnswerArgument":"<http://dbpedia.org/resource/Tico_Torres>","EntityName":"Tico Torres"},{"AnswerType":"Entity","AnswerArgument":"<http://dbpedia.org/resource/Aaron_Rossi>","EntityName":"Aaron Rossi"},{"AnswerType":"Entity","AnswerArgument":"<http://dbpedia.org/resource/Larry_Mullen,_Jr.>","EntityName":"Larry Mullen, Jr."},{"AnswerType":"Entity","AnswerArgument":"<http://dbpedia.org/resource/Longineu_W._Parsons_III>","EntityName":"Longineu W. Parsons III"},{"AnswerType":"Entity","AnswerArgument":"<http://dbpedia.org/resource/Babatunde_Lea>","EntityName":"Babatunde Lea"},{"AnswerType":"Entity","AnswerArgument":"<http://dbpedia.org/resource/Alfredo_Hernández>","EntityName":"Alfredo Hernández"},{"AnswerType":"Entity","AnswerArgument":"<http://dbpedia.org/resource/Raimund_Marasigan>","EntityName":"Raimund Marasigan"},{"AnswerType":"Entity","AnswerArgument":"<http://dbpedia.org/resource/Shinya_(musician)>","EntityName":"Shinya "},{"AnswerType":"Entity","AnswerArgument":"<http://dbpedia.org/resource/Collin_Leijenaar>","EntityName":"Collin Leijenaar"}]}}