{"QuestionId":"q1407","Parse":{"TopicEntityName":"Frank Rogers  record producer  ","TopicEntityMid":"<http://dbpedia.org/resource/Frank_Rogers_(record_producer)>","InferentialChain":["founders","the","record","labels","of","the","founders","frank","rogers"],"Constraints":[],"Answers":[{"AnswerType":"Entity","AnswerArgument":"<http://dbpedia.org/resource/Frank_Rogers_(record_producer)>","EntityName":"Frank Rogers "},{"AnswerType":"Entity","AnswerArgument":"<http://dbpedia.org/resource/Brad_Paisley>","EntityName":"Brad Paisley"},{"AnswerType":"Entity","AnswerArgument":"<http://dbpedia.org/resource/Chris_DuBois>","EntityName":"Chris DuBois"}]}}