{"QuestionId":"q1431","Parse":{"TopicEntityName":"Titus Software ","TopicEntityMid":"<http://dbpedia.org/resource/Titus_Software>","InferentialChain":["titus","software","publishes","genre","games"],"Constraints":[],"Answers":[{"AnswerType":"Entity","AnswerArgument":"<http://dbpedia.org/resource/Music_video_game>","EntityName":"Music video game"},{"AnswerType":"Entity","AnswerArgument":"<http://dbpedia.org/resource/Platform_game>","EntityName":"Platform game"},{"AnswerType":"Entity","AnswerArgument":"<http://dbpedia.org/resource/Music_game>","EntityName":"Music game"},{"AnswerType":"Entity","AnswerArgument":"<http://dbpedia.org/resource/Racing_video_game>","EntityName":"Racing video game"},{"AnswerType":"Entity","AnswerArgument":"<http://dbpedia.org/resource/Fighting_game>","EntityName":"Fighting game"},{"AnswerType":"Entity","AnswerArgument":"<http://dbpedia.org/resource/Isometric_projection>","EntityName":"Isometric projection"},{"AnswerType":"Entity","AnswerArgument":"<http://dbpedia.org/resource/Strategy>","EntityName":"Strategy"},{"AnswerType":"Entity","AnswerArgument":"<http://dbpedia.org/resource/Puzzle_video_game>","EntityName":"Puzzle video game"},{"AnswerType":"Entity","AnswerArgument":"<http://dbpedia.org/resource/Chess>","EntityName":"Chess"},{"AnswerType":"Entity","AnswerArgument":"<http://dbpedia.org/resource/Shooter_game>","EntityName":"Shooter game"}]}}