{"QuestionId":"q371","Parse":{"TopicEntityName":"GM B platform ","TopicEntityMid":"<http://dbpedia.org/resource/GM_B_platform>","InferentialChain":["cars","gm","b","base"],"Constraints":[],"Answers":[{"AnswerType":"Entity","AnswerArgument":"<http://dbpedia.org/resource/Pontiac_Chieftain>","EntityName":"Pontiac Chieftain"},{"AnswerType":"Entity","AnswerArgument":"<http://dbpedia.org/resource/Buick_Century>","EntityName":"Buick Century"},{"AnswerType":"Entity","AnswerArgument":"<http://dbpedia.org/resource/Buick_Invicta>","EntityName":"Buick Invicta"},{"AnswerType":"Entity","AnswerArgument":"<http://dbpedia.org/resource/Chevrolet_210>","EntityName":"Chevrolet 210"},{"AnswerType":"Entity","AnswerArgument":"<http://dbpedia.org/resource/Pontiac_G8>","EntityName":"Pontiac G8"},{"AnswerType":"Entity","AnswerArgument":"<http://dbpedia.org/resource/Chevrolet_Impala>","EntityName":"Chevrolet Impala"},{"AnswerType":"Entity","AnswerArgument":"<http://dbpedia.org/resource/North_America>","EntityName":"North America"},{"AnswerType":"Entity","AnswerArgument":"<http://dbpedia.org/resource/Mexico>","EntityName":"Mexico"},{"AnswerType":"Entity","AnswerArgument":"<http://dbpedia.org/resource/Chevrolet_Lumina>","EntityName":"Chevrolet Lumina"},{"AnswerType":"Entity","AnswerArgument":"<http://dbpedia.org/resource/Buick_Wildcat>","EntityName":"Buick Wildcat"},{"AnswerType":"Entity","AnswerArgument":"<http://dbpedia.org/resource/Chevrolet_Brookwood>","EntityName":"Chevrolet Brookwood"},{"AnswerType":"Entity","AnswerArgument":"<http://dbpedia.org/resource/Chevrolet_150>","EntityName":"Chevrolet 150"},{"AnswerType":"Entity","AnswerArgument":"<http://dbpedia.org/resource/Pontiac_Torpedo>","EntityName":"Pontiac Torpedo"},{"AnswerType":"Entity","AnswerArgument":"<http://dbpedia.org/resource/Pontiac_Star_Chief>","EntityName":"Pontiac Star Chief"},{"AnswerType":"Entity","AnswerArgument":"<http://dbpedia.org/resource/Pontiac_Bonneville>","EntityName":"Pontiac Bonneville"},{"AnswerType":"Entity","AnswerArgument":"<http://dbpedia.org/resource/Chevrolet_Biscayne>","EntityName":"Chevrolet Biscayne"},{"AnswerType":"Entity","AnswerArgument":"<http://dbpedia.org/resource/Chevrolet_Yeoman>","EntityName":"Chevrolet Yeoman"},{"AnswerType":"Entity","AnswerArgument":"<http://dbpedia.org/resource/Oldsmobile_88>","EntityName":"Oldsmobile 88"}]}}