{"QuestionId":"q4422","Parse":{"TopicEntityName":"Christchurch ","TopicEntityMid":"<http://dbpedia.org/resource/Christchurch>","InferentialChain":["list","education","institute","engineers","alma","mater","christchurch"],"Constraints":[],"Answers":[{"AnswerType":"Entity","AnswerArgument":"<http://dbpedia.org/resource/Christchurch>","EntityName":"Christchurch"},{"AnswerType":"Entity","AnswerArgument":"<http://dbpedia.org/resource/University_of_Canterbury>","EntityName":"University of Canterbury"},{"AnswerType":"Entity","AnswerArgument":"<http://dbpedia.org/resource/New_Zealand>","EntityName":"New Zealand"}]}}